README.md
setup.cfg
setup.py
ec2snap/__init__.py
ec2snap/ec2snap
ec2snap.egg-info/PKG-INFO
ec2snap.egg-info/SOURCES.txt
ec2snap.egg-info/dependency_links.txt
ec2snap.egg-info/requires.txt
ec2snap.egg-info/top_level.txt