Metadata-Version: 1.1
Name: ec2snap
Version: 0.5.4
Summary: Simple solution to backup ec2 instances using snapshots
Home-page: https://github.com/enovance/ec2_snapshot
Author: Pierre Mavro
Author-email: deimos@deimos.fr
License: UNKNOWN
Platform: UNKNOWN
Classifier: Programming Language :: Python
Classifier: Development Status :: 5 - Production/Stable
Classifier: License :: OSI Approved :: GNU General Public License v2 or later (GPLv2+)
Classifier: Environment :: Console
Classifier: Natural Language :: English
Classifier: Operating System :: OS Independent
Classifier: Programming Language :: Python :: 2.7
Classifier: Topic :: Communications
